random_readme_badges/__init__.py
random_readme_badges/main.py
random_readme_badges/models.py
random_readme_badges-0.1.0.dist-info/entry_points.txt
random_readme_badges-0.1.0.dist-info/LICENSE
random_readme_badges-0.1.0.dist-info/WHEEL
random_readme_badges-0.1.0.dist-info/METADATA
random_readme_badges-0.1.0.dist-info/RECORD
