Metadata-Version: 2.1
Name: random-readme-badges
Version: 0.1.0
Summary: Get random badges for badges' sake
Home-page: https://justine.kizhak.com/projects/random-readme-badges
License: MIT
Keywords: readme badges
Author: Justine Kizhakkinedath
Author-email: justine@kizhak.com
Requires-Python: >=3.7,<4.0
Classifier: Development Status :: 3 - Alpha
Classifier: License :: OSI Approved :: MIT License
Classifier: Operating System :: OS Independent
Classifier: Programming Language :: Python :: 3
Classifier: Programming Language :: Python :: 3.7
Classifier: Programming Language :: Python :: 3.8
Requires-Dist: click (>=7.1.2,<8.0.0)
Project-URL: Bug Reports, https://gitlab.com/justinekizhak/random-readme-badges/issues
Project-URL: Repository, https://gitlab.com/justinekizhak/random-readme-badges
Project-URL: Say Thanks!, https://saythanks.io/to/justine%40kizhak.com
